{"desc": "Wenlin Studio designs and produces hand embroidered textile products in Pakistan and UK, with contemporary aesthetic and traditional craft.", "file_name": "FaceDT.jpg", "size": [1024, 528], "layout": [{"type": "background", "position": [0, 0, 1024, 528], "text": ""}, {"type": "static-text", "position": [62, 212, 306, 33], "text": "ARTISAN EMBROIDERIES"}, {"type": "link-button", "position": [120, 279, 190, 42], "text": "SHOP NOW"}, {"type": "button", "position": [487, 506, 10, 10], "text": "1"}, {"type": "button", "position": [507, 506, 10, 10], "text": "2"}, {"type": "button", "position": [527, 506, 10, 10], "text": "3"}]}