{"desc": "Buy sustainable and high quality Kawayan Wooden watches. The best wooden watch brand that offers unique gifts for men and women, eco-friendly and sustainable design. Handcrafted with only the best materials.", "file_name": "KAWAYAN-hero1_1296x.png", "size": [1024, 600], "layout": [{"type": "background", "position": [0, 0, 1024, 600], "text": ""}, {"type": "static-text", "position": [30, 169, 964, 161], "text": "See the World From a Different Perspective"}, {"type": "link-button", "position": [30, 336, 142, 58], "text": "SHOP NOW"}, {"type": "button", "position": [488, 560, 16, 16], "text": "1"}, {"type": "button", "position": [520, 560, 16, 16], "text": "2"}]}