{"desc": "FAVORAH provides you with the latest trendy products, that you may have seen online, and also everyday essentials making it a one stop shop for your shopping needs", "file_name": "happy_puppy_compressed_pic_1080x.jpg", "size": [1024, 600], "layout": [{"type": "background", "position": [0, 0, 1024, 600], "text": ""}, {"type": "static-text", "position": [30, 234, 964, 130], "text": "Discover Your New Favourite Products"}, {"type": "link-button", "position": [442, 371, 140, 60], "text": "Shop Now"}]}