{"desc": "Variety of high-quality, handcrafted, all-natural and organic products made with loving intentions. As a company founded by a registered nurse and holistic healer, each product is intentionally designed to integrate the mind - body - spirit connection.", "file_name": "surrender.jpg", "size": [1024, 560], "layout": [{"type": "background", "position": [0, 0, 1024, 560], "text": ""}, {"type": "static-text", "position": [265, 263, 495, 97], "text": "NATURAL. INTENTIONAL. HOLISTIC."}, {"type": "static-text", "position": [267, 379, 490, 18], "text": "Treat your mind, body, and spirit to the Magic of Mother Nature."}, {"type": "static-text", "position": [451, 423, 122, 47], "text": "Shop all"}]}