{"desc": "Help yourself by helping our home. At Ethical Earth, we offer a wide variety of eco-friendly products.", "file_name": "EthicalStockPhoto.jpg", "size": [1024, 830], "layout": [{"type": "static-text", "position": [55, 279, 914, 102], "text": "Ethical Earth"}, {"type": "static-text", "position": [169, 389, 686, 36], "text": "Help yourself by helping our home"}, {"type": "link-button", "position": [427, 453, 170, 43], "text": "START SHOPPING"}, {"type": "background", "position": [0, 0, 1024, 775], "text": ""}]}