{"desc": "Diller Greenhouses is a local, family-owned and operated greenhouse located in Council Bluffs, Iowa. For three generations we have offered our customers quality plants, great selection and customer service.", "file_name": "IMG_7132_1080x.JPG", "size": [1024, 530], "layout": [{"type": "background", "position": [0, 0, 1024, 475], "text": ""}, {"type": "static-text", "position": [55, 22, 914, 237], "text": "Greenhouses are closed for the season. Opening again mid April 2023"}, {"type": "static-text", "position": [58, 269, 907, 96], "text": "LOCALLY GROWN & FAMILY OWNED Feel good knowing you\u2019re supporting a local family business whose three generations have served the Council Bluffs + Omaha metro area for almost 100 years."}, {"type": "link-button", "position": [415, 400, 194, 51], "text": "SEE OUR SELECTION"}, {"type": "image", "position": [417, 442, 11, 11], "text": ""}, {"type": "image", "position": [548, 442, 11, 11], "text": ""}, {"type": "image", "position": [396, 426, 187, 44], "text": ""}, {"type": "image", "position": [601, 443, 10, 10], "text": ""}]}