{"desc": "Welcome to Grace Jacob - We specialise in luxury swimwear and loungewear including Bikinis and Tracksuits- Shop The Collection", "file_name": "GJ-desktop-2022_1500x.jpg", "size": [1024, 500], "layout": [{"type": "background", "position": [0, 0, 1024, 500], "text": ""}, {"type": "static-text", "position": [194, 118, 635, 150], "text": "ISLAND COLLECTION"}, {"type": "static-text", "position": [418, 338, 187, 44], "text": "Shop the collection"}, {"type": "image", "position": [0, 0, 1024, 500], "text": ""}]}