{"desc": "Looking for 100% natural joint supplements? Vitahub offers the best joint supplement product made from Greenshell mussels that are sourced from New Zealand.  Vitahub.Health", "file_name": "-1633231844434main-glue-of-life3", "size": [1009, 770], "layout": [{"type": "image", "position": [80, 236, 409, 105], "text": ""}, {"type": "static-text", "position": [80, 382, 409, 63], "text": "NEW ZEALAND GREENSHELL\u2122 MUSSEL\n100% NATURAL JOINT HEALTH FORMULA"}, {"type": "link-button", "position": [80, 485, 141, 35], "text": "SHOP NOW"}, {"type": "background", "position": [0, 35, 1009, 686], "text": ""}, {"type": "submit", "position": [949, 358, 40, 40], "text": ""}, {"type": "submit", "position": [480, 701, 20, 5], "text": ""}, {"type": "submit", "position": [510, 701, 20, 5], "text": ""}]}