{"desc": "Mizzli Art offers custom products for your interior and exterior solutions 3D sign for your business, wall art stickers, custom painting, wall papers and many other products", "file_name": "3_1728x.jpg", "size": [1024, 750], "layout": [{"type": "button", "position": [0, 0, 12, 2], "text": ""}, {"type": "background", "position": [0, 0, 1024, 750], "text": ""}, {"type": "static-text", "position": [312, 310, 401, 80], "text": "ART SHOP"}, {"type": "static-text", "position": [408, 395, 208, 33], "text": "With Custom Products"}, {"type": "link-button", "position": [464, 443, 90, 40], "text": "SHOP"}, {"type": "button", "position": [357, 737, 150, 13], "text": "1"}, {"type": "button", "position": [517, 737, 150, 13], "text": "2"}]}