{"desc": "Colleen Annalea is an art and surface Illustration creative business offering handmade Christmas collectible ornaments, watercolor originals and prints, tea towels and stationary note cards and journals to add beauty and goodness to your home and life.", "file_name": "Shopify_resized_image_1500x.jpg", "size": [1024, 560], "layout": [{"type": "background", "position": [0, 0, 1024, 560], "text": ""}, {"type": "static-text", "position": [372, 343, 279, 52], "text": "Colleen Annalea"}, {"type": "link-button", "position": [452, 415, 121, 45], "text": "Shop all"}, {"type": "image", "position": [287, 293, 450, 217], "text": ""}]}