{"desc": "Custom Logo Uniforms. Custom apparel printing, custom logo embroidery and vinyl printing. Staff apparel, uniform programs, safety and visibility, branding and promotions Workwear, Dress shirts, Hats, Jackets, Polo shirts, Knits shirts.", "file_name": "rightuniform-banner3_1200x.jpg", "size": [1024, 520], "layout": [{"type": "background", "position": [0, 0, 1024, 520], "text": ""}, {"type": "static-text", "position": [478, 478, 12, 12], "text": ""}, {"type": "static-text", "position": [506, 478, 12, 12], "text": ""}, {"type": "static-text", "position": [534, 478, 12, 12], "text": ""}]}