{"desc": "artisanal jewellery combining digital & biological compositions bold & unique like every broken heart", "file_name": "DSCF6249site_bd3a10e1-024e-4da1-adec-09acc632e4fb_1500x.jpg", "size": [1009, 720], "layout": [{"type": "background", "position": [0, 0, 1009, 720], "text": ""}, {"type": "static-text", "position": [345, 374, 320, 129], "text": "time defining fine jewellery"}, {"type": "static-text", "position": [318, 530, 372, 19], "text": "combining digital design & natural compositions"}, {"type": "link-button", "position": [444, 575, 122, 45], "text": "shop all"}]}