{"desc": "Safe1 Safety Products is a leading supplier of workwear, footwear, work boots and safety equipment for men and women. Discover our range online today!", "file_name": "COREY-01_1600x.jpg", "size": [1024, 427], "layout": [{"type": "background", "position": [0, 0, 1024, 427], "text": ""}, {"type": "static-text", "position": [285, 117, 455, 115], "text": "V-CHEK RAPID ANTIGEN TESTS NOW IN STOCK"}, {"type": "link-button", "position": [442, 255, 141, 44], "text": "ORDER NOW"}, {"type": "image", "position": [255, 87, 514, 253], "text": ""}]}