{"desc": "Coffee Gear Online caters to both baristas and home coffee enthusiasts. All the coffee equipment you need is here. From coffee machines, coffee cups, coffee filters, coffee brewing equipment and more.", "file_name": "hero1_1080x.jpg", "size": [1024, 530], "layout": [{"type": "static-text", "position": [55, 177, 914, 78], "text": "Coffee Gear Online"}, {"type": "static-text", "position": [169, 263, 686, 36], "text": "Performance coffee equipment for home, office or cafe."}, {"type": "background", "position": [0, 0, 1024, 475], "text": ""}]}