{"desc": "Create canvas prints, framed prints, photos on canvas, collage prints & instagram prints in minutes. Dublin: 01 524 2419. Cork: 021 4700972.", "file_name": "Shop_Wall.jpg", "size": [1036, 694], "layout": [{"type": "static-text", "position": [15, 244, 1006, 36], "text": "Canvas - Framed - Wood Mount - Collage"}, {"type": "static-text", "position": [15, 279, 1006, 81], "text": "ORDER NOW FOR FATHER'S DAY!"}, {"type": "link-button", "position": [378, 379, 280, 60], "text": "PRINT YOUR PHOTOS"}, {"type": "background", "position": [0, 0, 1036, 694], "text": ""}]}