{"desc": "Shop natural essential oils soy candles, cement home decor, throw pillows and more. Our passion is to create and curate simple and timeless handmade artisan home accents to inspire you to create a home filled with beauty, life and rest.", "file_name": "hero.jpg", "size": [1024, 824], "layout": [{"type": "static-text", "position": [0, 200, 1024, 102], "text": "SUMMER FAVORITES"}, {"type": "link-button", "position": [442, 312, 140, 46], "text": "SHOP NOW"}, {"type": "image", "position": [0, 0, 1024, 558], "text": ""}, {"type": "image", "position": [0, 0, 1024, 558], "text": ""}, {"type": "static-text", "position": [0, 0, 1024, 558], "text": ""}, {"type": "image", "position": [0, 0, 1024, 558], "text": ""}, {"type": "static-text", "position": [0, 559, 1024, 256], "text": "HANDMADE GOODS\nTO MAKE YOUR HOME A PLACE OF\nBEAUTY, LIFE & REST"}, {"type": "background", "position": [0, 0, 1024, 814], "text": ""}, {"type": "image", "position": [0, 0, 1024, 814], "text": ""}, {"type": "image", "position": [0, 0, 1024, 814], "text": ""}]}