{"desc": "Shop 46 & Spruce to find inspirational home and garden decor including vases, floral supplies, terrariums, planters, gardening gifts, and more!", "file_name": "slide_2.jpg", "size": [1024, 485], "layout": [{"type": "image", "position": [39, 234, 12, 17], "text": ""}, {"type": "image", "position": [20, 10, 176, 448], "text": ""}, {"type": "background", "position": [20, 10, 984, 448], "text": ""}, {"type": "static-text", "position": [40, 89, 350, 20], "text": "NEW DESIGN BOOK"}, {"type": "static-text", "position": [40, 114, 350, 89], "text": "SYMPATHY STYLING"}, {"type": "static-text", "position": [40, 207, 350, 24], "text": "Inspired Designs to Celebrate Life!"}, {"type": "static-text", "position": [120, 270, 190, 24], "text": "$49.99 \u2022 Now Available!"}, {"type": "link-button", "position": [60, 340, 310, 51], "text": "ORDER YOURS TODAY!"}, {"type": "image", "position": [973, 234, 12, 17], "text": ""}]}