{"desc": "No wires. No tubes. No noise to announce you're pumping.", "file_name": "image_4.png", "size": [1024, 797], "layout": [{"type": "static-text", "position": [532, 140, 472, 285], "text": "Do it all while you pump"}, {"type": "static-text", "position": [532, 425, 472, 127], "text": "Emails, drive, shop - Mon Lait is the hands-free solution to pumping."}, {"type": "link-button", "position": [532, 582, 164, 50], "text": "ORDER NOW"}, {"type": "background", "position": [0, 0, 1024, 772], "text": ""}, {"type": "image", "position": [263, 758, 23, 21], "text": ""}, {"type": "image", "position": [291, 758, 23, 21], "text": ""}, {"type": "image", "position": [319, 758, 23, 21], "text": ""}, {"type": "image", "position": [347, 758, 23, 21], "text": ""}, {"type": "image", "position": [375, 758, 23, 21], "text": ""}, {"type": "static-text", "position": [405, 749, 55, 47], "text": "4.8"}, {"type": "static-text", "position": [467, 751, 294, 43], "text": "Based on 68 reviews"}]}