{"desc": "Not Sucky designs and fabricates low cost products such as flatpack, DIY kits, home or office furnishes to custom guitars. Casual DYO (Design Your Own) services with house to fabrication services. We Fabricate Small Run Products For You. Become one of our artists / designers and let us do the making.", "file_name": "notsucky_branding_no_logos_1280x600_6034c57a-48ec-4a7e-855f-71c876b25b01_1080x.jpg", "size": [1024, 530], "layout": [{"type": "static-text", "position": [55, 119, 914, 38], "text": "Not Sucky - Flat Pack Furniture Kits : Flat Pack Products"}, {"type": "static-text", "position": [169, 166, 686, 120], "text": "Affordable decor designed with cascadence / expandability in mind.\nPersonalization or finishing by you to suit an individual aesthetic.\nNatural birch, pre-primed for DIY painting, or painted ready to go.\nBecome one of our artists - We will fabricate your ideas."}, {"type": "link-button", "position": [471, 313, 82, 43], "text": "SHOP"}, {"type": "background", "position": [0, 0, 1024, 475], "text": ""}]}