{"desc": "High Quality Generators to fit Every Need. Never be left without power with our large selection of powerful and reliable generators.", "file_name": "house-storm-generator2_2048x.progressive.jpg", "size": [1090, 629], "layout": [{"type": "background", "position": [8, 0, 1074, 614], "text": ""}, {"type": "static-text", "position": [8, 153, 1074, 118], "text": "NEVER GO WITHOUT POWER"}, {"type": "static-text", "position": [8, 270, 1074, 135], "text": "FREE SHIPPING IN THE USA! NO TAX! -We Supply Only The Most Reliable Power Generators for your Power Needs. Shipped Fast & Direct To your Door. OUTSIDE of the USA? Send us an Email and we'll quote the shipping for you."}, {"type": "link-button", "position": [426, 419, 238, 41], "text": "See all Our Power Generators"}, {"type": "static-text", "position": [531, 587, 9, 9], "text": ""}, {"type": "static-text", "position": [550, 587, 9, 9], "text": ""}]}