{"desc": "Elevate your spirits with Flighty Premium Mixers cocktail mix. Just add alcohol for cocktails or seltzer water for mocktails. No fuss, no mess. Shop now!", "file_name": "Untitled-12_1600x.png", "size": [1024, 576], "layout": [{"type": "background", "position": [0, 0, 1024, 576], "text": ""}, {"type": "static-text", "position": [580, 77, 366, 297], "text": "PREMIUM COCKTAIL MIX - JUST ADD SPIRITS!"}, {"type": "static-text", "position": [542, 403, 441, 18], "text": "No fuss. No mess. No fancy bar tools. Just Add Spirits!"}, {"type": "link-button", "position": [655, 445, 215, 65], "text": "Get your 4-pack today!"}]}