{"desc": "Saltwater fish, Corals, Inverts, Dry Goods and live rock are in stock and ready for purchase. You can order online and pick up curb side, or have your order shipped anywhere to the 48 contiguous states. If you don't see something you're looking don't hesitate to send us a message here on our facebook page.", "file_name": "BANNER_SLIDER_1400_X_500_3_1080x.png", "size": [1024, 421], "layout": [{"type": "background", "position": [0, 0, 1024, 366], "text": ""}, {"type": "link-button", "position": [451, 157, 122, 53], "text": "SHOP NOW"}, {"type": "image", "position": [458, 334, 11, 11], "text": ""}, {"type": "image", "position": [553, 334, 11, 11], "text": ""}, {"type": "image", "position": [436, 317, 151, 44], "text": ""}]}