{"desc": "JAR UK Industries is a leading supplier of workshop consumables, supplies and accessories for the automotive, garage, agricultural and marine industries. We offer free delivery across the UK. Trade and wholesale pricing across our website. Assortments, bulbs, lubricants, electrical, fasteners, fixings and more...", "file_name": "Heatshrink_Front_Page_Image_6e19523b-49ac-4348-a2a5-ae3a7211bca9_1024x512_crop_center.jpg", "size": [1024, 500], "layout": [{"type": "static-text", "position": [0, 0, 1024, 500], "text": ""}, {"type": "background", "position": [0, 0, 1024, 500], "text": ""}, {"type": "static-text", "position": [0, 168, 1024, 42], "text": "Heat Shrink - In all sizes"}, {"type": "static-text", "position": [0, 222, 1024, 28], "text": "4:1 | 3:1 | 2:1 | Cut to length"}, {"type": "link-button", "position": [420, 280, 185, 51], "text": "View the Range"}]}