{"desc": "We are an online retailer of fishing gear and outdoors products, and we provide good quality items in an unbelivable price.", "file_name": "3_7f2d6a60-d1c3-4dfc-8920-206d7f38ca53.jpg", "size": [1024, 475], "layout": [{"type": "background", "position": [0, 0, 1024, 475], "text": ""}, {"type": "static-text", "position": [55, 160, 914, 70], "text": "SPRING SALES NOW"}, {"type": "static-text", "position": [169, 225, 686, 33], "text": "BEST PRODUCTS WITH UNBEATABLE PRICE"}, {"type": "static-text", "position": [443, 273, 138, 36], "text": "MORE DETAILS"}, {"type": "button", "position": [506, 436, 12, 12], "text": "1"}]}