{"desc": "All Natural Scented Soy Candles.", "file_name": "Homepage_1296x.png", "size": [1024, 705], "layout": [{"type": "static-text", "position": [55, 137, 914, 159], "text": "The Best Smelling Natural Candles"}, {"type": "static-text", "position": [169, 303, 686, 138], "text": "Meeting HHI's sustainability mantra is key for all our candles. That is why we choose to make every candle with ecofriendly soy wax, natural fragrance, add no paraffin and use all-natural bamboo lid."}, {"type": "link-button", "position": [399, 468, 226, 41], "text": "AVAILABLE FRAGRANCES"}, {"type": "background", "position": [0, 0, 1024, 650], "text": ""}]}