{"desc": "Auto-Fill is a privately owned company located in Dothan, Alabama committed to manufacturing the highest quality Made in USA products. These products include automatic feeding & watering systems for pets, fowl, poultry, livestock, wild game and more.....", "file_name": "slide-image-2.jpg", "size": [1024, 576], "layout": [{"type": "background", "position": [0, 0, 1024, 512], "text": ""}, {"type": "static-text", "position": [288, 180, 448, 89], "text": "BECOME A DEALER"}, {"type": "static-text", "position": [40, 263, 945, 24], "text": "DO YOU PLAN TO CARRY AUTO-FILL IN YOUR STORES? BECOME A VENDOR AND SAVE ON BULK ORDERS."}, {"type": "static-text", "position": [377, 287, 270, 61], "text": "SEE INVENTORY"}, {"type": "link-button", "position": [462, 476, 16, 18], "text": "1"}, {"type": "link-button", "position": [490, 476, 16, 18], "text": "2"}, {"type": "link-button", "position": [518, 476, 16, 18], "text": "3"}, {"type": "link-button", "position": [546, 476, 16, 18], "text": "4"}, {"type": "image", "position": [50, 517, 145, 54], "text": ""}, {"type": "image", "position": [899, 512, 62, 64], "text": ""}, {"type": "static-text", "position": [379, 533, 32, 22], "text": "HOME"}, {"type": "static-text", "position": [439, 533, 55, 22], "text": "ABOUT US"}, {"type": "static-text", "position": [522, 524, 73, 52], "text": "PRODUCTS"}, {"type": "static-text", "position": [623, 524, 67, 52], "text": "SERVICES"}, {"type": "static-text", "position": [718, 524, 64, 52], "text": "SUPPORT"}, {"type": "static-text", "position": [810, 533, 69, 22], "text": "CONTACT US"}]}