{"desc": "Entiny Prints Create unique Personalized gifts online for Grandma, Grandpa, Mom, Dad, Dog & Cat lovers at Entiny Prints, upload and print your favorite photos on shirts, pillows, mugs, tumblers and more.", "file_name": "6cbae28a2f5eee00b74f_1500x.jpg", "size": [1024, 345], "layout": [{"type": "background", "position": [50, 10, 924, 309], "text": ""}, {"type": "image", "position": [19, 159, 26, 26], "text": ""}, {"type": "image", "position": [979, 159, 26, 26], "text": ""}, {"type": "static-text", "position": [507, 332, 10, 10], "text": ""}]}