{"desc": "The stylish intersection where black excellence and quality merge. Your HBCU elevates your collegiate threads in a fresh direction with a promise of exclusive variety.", "file_name": "FAMU_2_1728x.jpg", "size": [1024, 576], "layout": [{"type": "button", "position": [25, 263, 50, 50], "text": "Previous"}, {"type": "background", "position": [0, 0, 1024, 576], "text": ""}, {"type": "button", "position": [949, 263, 50, 50], "text": "Next"}, {"type": "button", "position": [462, 533, 11, 11], "text": "1"}, {"type": "button", "position": [484, 533, 11, 11], "text": "2"}, {"type": "button", "position": [506, 533, 11, 11], "text": "3"}, {"type": "button", "position": [528, 533, 11, 11], "text": "4"}, {"type": "button", "position": [550, 533, 11, 11], "text": "5"}]}