{"desc": "Portable Jump Starters featuring INTELLIBOOST safe boosting technology. RG1000 Features USB charging, portable power solutions, emergency flashlight, and more!", "file_name": "RG1000S_underhood_1920x700_banner_1920x.jpg", "size": [1024, 373], "layout": [{"type": "static-text", "position": [31, 103, 963, 50], "text": "The new RG1000S is here."}, {"type": "static-text", "position": [31, 157, 963, 30], "text": "Be safe, put one in all your vehicles."}, {"type": "link-button", "position": [396, 219, 232, 48], "text": "SHOP NOW"}, {"type": "background", "position": [0, 0, 1024, 373], "text": ""}, {"type": "button", "position": [482, 337, 18, 18], "text": "1"}, {"type": "button", "position": [512, 337, 18, 18], "text": "2"}, {"type": "button", "position": [542, 337, 18, 18], "text": "3"}]}