{"desc": "We are a trusted store offering KPOP / Korean Drama Trends in the PH Philippines. Our best sellers are SE-RI Gentle monster inspired Sunglasses, Jennie Kuku Inspired Sunglasses, Korean Slides inspired by Yeezy Slides minimalist designs and modern apparel. Discounts, Buy 1 Take 1 Promotion and SALE available.", "file_name": "Gold_BG_1500x.jpg", "size": [1024, 720], "layout": [{"type": "background", "position": [0, 0, 1024, 720], "text": ""}, {"type": "static-text", "position": [236, 399, 552, 156], "text": "We offer Korean Pop Culture Trends with the best quality and affordable price"}, {"type": "link-button", "position": [419, 575, 186, 45], "text": "KOREAN APPAREL"}]}