{"desc": "Stock Vector Collections For Commercial Use.", "file_name": "slider_backdrop2.jpg", "size": [1024, 500], "layout": [{"type": "static-text", "position": [77, 67, 292, 94], "text": "The Space\nCrackle Brush"}, {"type": "static-text", "position": [369, 105, 25, 56], "text": "+"}, {"type": "static-text", "position": [77, 166, 398, 207], "text": "Recreate the popular \u201cCrackle\u201d comic book technique with this easy to use Adobe Illustrator CC Brush! Great for Illustrators and Graphic Designers to give your comic book themed projects that authentic 1970\u2019s feel. Purchase yours today and harness the power of the Universe!"}, {"type": "static-text", "position": [77, 395, 236, 21], "text": "Available Formats: .AI | .EPS"}, {"type": "link-button", "position": [77, 437, 190, 50], "text": "DETAILS"}, {"type": "link-button", "position": [277, 437, 190, 50], "text": "BUY NOW"}, {"type": "image", "position": [517, 93, 430, 320], "text": ""}, {"type": "background", "position": [0, 0, 1024, 500], "text": ""}, {"type": "static-text", "position": [0, 0, 90, 30], "text": "NEW"}]}