{"desc": "We\u2019ve been in the specialty oils business for more than 18 years. Our oils are made with the finest seeds and fruit, all produced in selected micro-climates around New Zealand. Rich in Omega 3, Omega 6 and Omega 9 with fantastic health benefits..", "file_name": "Site-banner-new-v2_1728x.jpg", "size": [1024, 650], "layout": [{"type": "background", "position": [0, 0, 1024, 650], "text": ""}, {"type": "static-text", "position": [55, 202, 914, 116], "text": "HEALTHY OMEGAS"}, {"type": "static-text", "position": [169, 320, 686, 35], "text": "100% NEW ZEALAND PURE"}, {"type": "link-button", "position": [435, 385, 154, 59], "text": "SHOP NOW"}]}