{"desc": "Accessories, Performance & Products for BMW, Porsche, Audi, VW and Mercedes Benz", "file_name": "DSC06702_1024x.progressive.jpg", "size": [1024, 683], "layout": [{"type": "background", "position": [0, 0, 1024, 683], "text": ""}, {"type": "button", "position": [674, 644, 48, 5], "text": "1"}, {"type": "button", "position": [732, 644, 48, 5], "text": "2"}, {"type": "button", "position": [790, 644, 48, 5], "text": "3"}, {"type": "button", "position": [848, 644, 48, 5], "text": "4"}, {"type": "button", "position": [906, 644, 48, 5], "text": "5"}]}