{"desc": "Pullen Surf Skis is a 100% Australian owned business dedicated to the manufacture high quality water-sports and surf equipment. For over six decades, Pullen has has produced products including wave skis, surf life saving racing skis, leisure and resort craft, canoes, kayaks, paddles and accessories. MADE IN AUSTRALIA", "file_name": "Artboard_5_2160x.jpg", "size": [1024, 512], "layout": [{"type": "background", "position": [0, 0, 1024, 512], "text": ""}, {"type": "static-text", "position": [88, 64, 460, 17], "text": "FIND OUT ABOUT OUR"}, {"type": "static-text", "position": [88, 108, 460, 61], "text": "CORAL"}, {"type": "static-text", "position": [88, 160, 460, 61], "text": "VIEWER"}, {"type": "link-button", "position": [88, 256, 176, 52], "text": "LEARN MORE"}, {"type": "submit", "position": [319, 454, 65, 36], "text": "Go to slide 1"}, {"type": "submit", "position": [399, 454, 65, 36], "text": "Go to slide 2"}, {"type": "submit", "position": [479, 454, 65, 36], "text": "Go to slide 3"}, {"type": "submit", "position": [559, 454, 65, 36], "text": "Go to slide 4"}, {"type": "submit", "position": [639, 454, 65, 36], "text": "Go to slide 5"}]}