{"desc": "We\u2019ve been in the measurement business for over 150 years\u2026 which is why Taylor is the brand you can trust.", "file_name": "SRG_June2022_Banner-2880x1440_2000x.jpg", "size": [1049, 652], "layout": [{"type": "static-text", "position": [64, 64, 396, 21], "text": "NEW TO THE RAIN GAUGE MARKET!"}, {"type": "static-text", "position": [64, 89, 396, 347], "text": "THE SILICONE RAIN GAUGE"}, {"type": "static-text", "position": [64, 444, 396, 80], "text": "Designed for year-round use, the durable and flexible silicone tube expands should temperatures dip below freezing. This shatterproof design eliminates the need to empty or bring your rain gauge indoors during inclement weather."}, {"type": "link-button", "position": [64, 540, 160, 44], "text": "SHOP"}, {"type": "image", "position": [64, 64, 396, 524], "text": ""}, {"type": "background", "position": [0, 0, 1049, 652], "text": ""}]}