{"desc": "A haven dedicated to fulfilling all spiritual paths. We stock ethically sourced crystals, pure essential oils, incense, sterling silver and gemstone jewellery, tarot and oracle decks, books, Himalayan salt products, crystal lamps, t.light holders and much much more.", "file_name": "crystal-header-images_3a0dd0bf-a304-4347-994b-6b7b97bdcba2.jpg", "size": [1024, 705], "layout": [{"type": "static-text", "position": [55, 246, 914, 81], "text": "MIND, BODY, SOUL"}, {"type": "static-text", "position": [169, 334, 686, 69], "text": "Ethically sourced beautiful crystals, incense, books, essential oils, jewellery, candles, tarot/oracle cards and gifts."}, {"type": "background", "position": [0, 0, 1024, 650], "text": ""}]}