{"desc": "Styling We make style and fashion effortless, invest time and effort in your wardrobe so you don\u2019t have to. We handle your style needs while you take over the world. We assist in bringing out your confidence, in dressing to the position which God.", "file_name": "Image_ee4215ef-4dd5-4714-afd1-b8d22f0e3346_300x.jpg", "size": [1024, 1024], "layout": [{"type": "background", "position": [0, 0, 1024, 1024], "text": ""}, {"type": "static-text", "position": [40, 426, 944, 28], "text": "GARMENTS FOR GLORY AND FOR BEAUTY"}, {"type": "static-text", "position": [40, 469, 944, 80], "text": "HOLY APPAREL"}, {"type": "link-button", "position": [852, 569, 133, 44], "text": "SHOP NOW"}, {"type": "submit", "position": [18, 974, 50, 50], "text": ""}, {"type": "submit", "position": [958, 974, 50, 50], "text": ""}]}