{"desc": "StudioBeej is a sustainable fashion and lifestyle brand. Hand crafted and made in small batches our products are ethical and stylish. \u2713 Ship Worldwide \u2713 Certified Vegan", "file_name": "card-wallet-desk-banner-4.jpg", "size": [1024, 427], "layout": [{"type": "image", "position": [0, 0, 118, 427], "text": ""}, {"type": "background", "position": [0, 0, 1024, 427], "text": ""}, {"type": "button", "position": [478, 392, 14, 14], "text": "1"}, {"type": "button", "position": [504, 392, 14, 14], "text": "2"}, {"type": "button", "position": [530, 392, 14, 14], "text": "3"}]}