{"desc": "Ace of Spades is a fashion brand curated with NYC in mind. We have found a way to capture the rugged urban street wear we all love and merged it with the high fashion aesthete that the city is known for.", "file_name": "sherazz_banner_shirt_hoodies3_1600x.jpg", "size": [1024, 471], "layout": [{"type": "background", "position": [0, 0, 1024, 471], "text": ""}, {"type": "static-text", "position": [512, 136, 399, 26], "text": "Welcome to"}, {"type": "static-text", "position": [512, 173, 399, 53], "text": "Ace of Spades NYC"}, {"type": "static-text", "position": [512, 238, 399, 13], "text": "Be the Ace, No Matter How They Shuffle"}, {"type": "link-button", "position": [643, 281, 137, 44], "text": "SHOP NOW"}, {"type": "image", "position": [482, 106, 459, 258], "text": ""}]}