{"desc": "Original music for Ballet Class. CD, MP3s, PDFs, available for Download. Composed by Marina Surgan, principal pianist for Canada's National Ballet School. Inspire your Dancers!", "file_name": "Snapshot_15_1512x.png", "size": [1024, 830], "layout": [{"type": "static-text", "position": [55, 290, 914, 81], "text": "Music for Ballet Class"}, {"type": "static-text", "position": [169, 378, 686, 35], "text": "Barre & Center Practice"}, {"type": "link-button", "position": [439, 440, 146, 41], "text": "LISTEN INSIDE"}, {"type": "background", "position": [0, 0, 1024, 775], "text": ""}]}