{"desc": "The best 360\u00b0 kids' toothbrush on the planet. Automatic electric toothbrush for kids. Waterproof wireless rechargeable with smart timer and IPX7.", "file_name": "Untitled_design_3_1500x.png", "size": [1024, 720], "layout": [{"type": "background", "position": [0, 0, 1024, 720], "text": ""}, {"type": "static-text", "position": [328, 225, 369, 138], "text": "Brushing Made Easy."}, {"type": "static-text", "position": [330, 385, 363, 22], "text": "On a mission to make teeth brushing fun!"}, {"type": "link-button", "position": [430, 449, 164, 45], "text": "SHOP NOW"}]}