{"desc": "Dog Grooming, Cat Grooming, Pet Bowls, Pet Accessories ,Cat Collar, Dog Lead ,Pet Beds ,Unique Pet Gifts,Pet Safety,Pet Clothes,Pet Treats,Pet Measuring Spoon,Pet Diet ,", "file_name": "ohUkap3L1t2CtNCIW4wMM1U5XNAhd80mO7UtxE3Xn4nkk_XVZLJUiiCJVFV0X7CSly4EW5xj2KDvXqUw5cM1wWGqTIBCx13ujszM0n_OF5Rna4hPU93c8eFDnai6t9VsSTnCxPKHf9KlQUrXYX5puTzKA8nQkFrRA7sJ_pIE4W_qE29DZY5cSBR_1600x.jpg", "size": [1044, 696], "layout": [{"type": "background", "position": [0, 0, 1044, 696], "text": ""}, {"type": "static-text", "position": [40, 246, 349, 20], "text": "MY TRENDY GOODS"}, {"type": "static-text", "position": [40, 277, 323, 104], "text": "A Store That is Full of Surprise"}, {"type": "link-button", "position": [40, 403, 169, 34], "text": "View Products"}, {"type": "link-button", "position": [221, 403, 168, 34], "text": "View Collections"}]}