{"desc": "Turbo Solutions specialises in the supply of remanufactured and new turbochargers, as well as offering a comprehensive repair service from globally recognised makers Garrett, Mitsubishi, IHI, and Borgwarner.", "file_name": "shutterstock_609342818.jpg", "size": [1024, 458], "layout": [{"type": "background", "position": [0, 0, 1024, 450], "text": ""}, {"type": "static-text", "position": [81, 105, 278, 113], "text": "24 Month Warranty on Turbochargers"}, {"type": "static-text", "position": [81, 244, 278, 72], "text": "Give yourself peace of mind with a 24 month warranty as standard on all Turbochargers."}, {"type": "link-button", "position": [81, 325, 123, 47], "text": "View Turbos"}, {"type": "image", "position": [41, 58, 358, 334], "text": ""}]}