{"desc": "Welcome to the official Police South Africa website. Shop the latest Police watches, jewellery, accessories & sunglasses online now! Official online retailer for Police South Africa.", "file_name": "POLICE_WEB-02_1080x.jpg", "size": [1024, 400], "layout": [{"type": "button", "position": [22, 172, 38, 38], "text": "PREVIOUS"}, {"type": "background", "position": [0, 0, 1024, 400], "text": ""}, {"type": "static-text", "position": [824, 201, 119, 24], "text": "JEWELLERY"}, {"type": "link-button", "position": [824, 238, 119, 42], "text": "BROWSE"}, {"type": "button", "position": [948, 172, 38, 38], "text": "NEXT"}]}