{"desc": "UBioAccess provides End-to-End Plant and Security solution. Direct business Partnership UBio X | VIRDI from South Korea.", "file_name": "Ubio_X_1296x.jpg", "size": [1009, 705], "layout": [{"type": "background", "position": [0, 0, 1009, 650], "text": ""}, {"type": "static-text", "position": [55, 80, 899, 74], "text": "UBioAccess"}, {"type": "static-text", "position": [55, 165, 838, 27], "text": "UBioAccess - Daeun Corp. Global Supplier of Biometric Security Solution Provider"}, {"type": "link-button", "position": [55, 226, 217, 51], "text": "2021 PRODUCT BROCHURE"}]}