{"desc": "Advexure is one of North America's largest dealers, distributors and systems integrators for unmanned drone systems and technology solutions. We offer professional UAS equipment solutions for public safety, film & cinema, construction, and utilities.", "file_name": "1920_1080_1200x.png", "size": [1127, 430], "layout": [{"type": "static-text", "position": [40, 182, 1047, 40], "text": "Introducing the DJI Mavic 3 Series"}, {"type": "static-text", "position": [40, 229, 650, 56], "text": "Imaging Above Everything. DJI's new flagship camera drone.\n4/3 CMOS Hasselblad Camera, 5.1K Apple ProRes."}, {"type": "link-button", "position": [40, 307, 229, 48], "text": "Grab Your Mavic 3 Now"}, {"type": "background", "position": [0, 0, 1127, 430], "text": ""}, {"type": "image", "position": [0, 0, 1127, 430], "text": ""}, {"type": "static-text", "position": [488, 388, 12, 12], "text": ""}, {"type": "static-text", "position": [516, 388, 12, 12], "text": ""}, {"type": "static-text", "position": [544, 388, 12, 12], "text": ""}, {"type": "static-text", "position": [572, 388, 12, 12], "text": ""}, {"type": "static-text", "position": [600, 388, 12, 12], "text": ""}, {"type": "static-text", "position": [628, 388, 12, 12], "text": ""}]}