{"desc": "Nutritionist formulated, naturally cherry flavoured beauty gummy supplement that targets glowing skin, stronger hair and healthy nails. With Astaxhantin, Inulin, Biotin and Acai Berry extract. Vegan, high fiber, gluten free, halal friendly and less sugar than a single cherry.", "file_name": "Mobile-Mothers-Days-1200x900-very-high_1080x.jpg", "size": [1024, 475], "layout": [{"type": "static-text", "position": [358, 126, 308, 146], "text": "Thicker hair. Luminous skin. Stronger nails. Zero plastic."}, {"type": "link-button", "position": [444, 299, 136, 51], "text": "SHOP NOW"}, {"type": "background", "position": [0, 0, 1024, 475], "text": ""}]}