{"desc": "Plastic free and vegan Shampoo Conditioner Soaps Bath products and more. All handmade in small batches in Devon UK", "file_name": "lavender-in-shop_1080x.jpg", "size": [1024, 530], "layout": [{"type": "background", "position": [0, 0, 1024, 475], "text": ""}, {"type": "static-text", "position": [55, 150, 914, 48], "text": "Worldwide shipping"}, {"type": "static-text", "position": [233, 208, 558, 26], "text": "Natural Spa products are available to order worldwide."}, {"type": "link-button", "position": [352, 268, 320, 57], "text": "FIND YOUR SHIPPING RATE HERE"}, {"type": "image", "position": [429, 451, 11, 11], "text": ""}, {"type": "image", "position": [538, 451, 11, 11], "text": ""}, {"type": "image", "position": [415, 432, 149, 44], "text": ""}, {"type": "image", "position": [582, 450, 10, 10], "text": ""}]}