{"desc": "Farias Surf and Sport is celebrating 50 years as Long Beach Island's favorite surf and beach shop! Visit one of our 6 retail locations throughout LBI for the latest apparel, the biggest surfboard collection on the East Coast, and more!", "file_name": "Spring_2021_-_Edited-15_1600x.jpg", "size": [1009, 650], "layout": [{"type": "background", "position": [0, 0, 1009, 650], "text": ""}, {"type": "static-text", "position": [50, 234, 550, 60], "text": "BOARDS! BOARDS! BOARDS!"}, {"type": "static-text", "position": [50, 316, 550, 49], "text": "New boards are in! Come into the Ship Bottom shop to check out the full inventory!"}, {"type": "static-text", "position": [368, 629, 48, 8], "text": ""}, {"type": "static-text", "position": [424, 629, 48, 8], "text": ""}, {"type": "static-text", "position": [480, 629, 48, 8], "text": ""}, {"type": "static-text", "position": [536, 629, 48, 8], "text": ""}, {"type": "static-text", "position": [592, 629, 48, 8], "text": ""}, {"type": "image", "position": [10, 303, 27, 44], "text": ""}, {"type": "image", "position": [972, 303, 27, 44], "text": ""}]}