{"desc": "Cosy Aromas are one of the UK's fastest growing wax melts and candles brand. Buy our products at wholesale/trade rates for you to resell in your shop and business.", "file_name": "wax-melts-fragrance-oil_1080x.jpg", "size": [1024, 705], "layout": [{"type": "static-text", "position": [55, 136, 914, 156], "text": "Wholesale Wax Melts & Candles"}, {"type": "static-text", "position": [169, 300, 686, 144], "text": "Cosy Aromas is one of the UK's fastest growing home fragrance brands. Our products are very popular amongst our customers and we've now opened our wax melts and candles up for wholesale."}, {"type": "link-button", "position": [408, 471, 208, 43], "text": "CREATE AN ACCOUNT"}, {"type": "background", "position": [0, 0, 1024, 650], "text": ""}]}