{"desc": "Supplier of premium Jewellery and on-trend accessories. Available for purchase online. Express shipping straight to your door. Melbourne owned and operated. Shop local & support small business.", "file_name": "long-haired-woman.jpg", "size": [1024, 420], "layout": [{"type": "background", "position": [0, 0, 1024, 420], "text": ""}, {"type": "static-text", "position": [388, 129, 248, 52], "text": "Styled By Josh"}, {"type": "static-text", "position": [461, 195, 102, 23], "text": "Online Store"}, {"type": "link-button", "position": [287, 244, 220, 47], "text": "For Ladies"}, {"type": "link-button", "position": [517, 244, 220, 47], "text": "For Men"}]}