{"desc": "A helping hand for musicians who struggle with understanding the basics of music theory for dummies. Choose the alternative road together with Ossia Music! Please visit us and start learning music theory today!", "file_name": "Untitled_design_10_1080x.png", "size": [1024, 591], "layout": [{"type": "static-text", "position": [55, 152, 914, 82], "text": "OSSIA MUSIC"}, {"type": "static-text", "position": [320, 239, 385, 32], "text": "A proven method, a new approach"}, {"type": "link-button", "position": [342, 336, 340, 43], "text": "COMING SOON! GET YOUR INVITE HERE"}, {"type": "background", "position": [0, 0, 1024, 536], "text": ""}]}