{"desc": "Stargazing T-shirts, loved by adults and children alike. We\u2019re taking space t-shirts to a different level, with great designs that are out of this world! Printed and embroidered on quality t-shirts, hoodies, bags, hats and many more; all decorated in the Devon, UK.", "file_name": "No-Dumping-Banner_1512x.jpg", "size": [1009, 650], "layout": [{"type": "image", "position": [28, 313, 24, 24], "text": ""}, {"type": "background", "position": [0, 0, 1009, 650], "text": ""}, {"type": "image", "position": [957, 313, 24, 24], "text": ""}, {"type": "static-text", "position": [344, 598, 40, 2], "text": ""}, {"type": "static-text", "position": [400, 598, 40, 2], "text": ""}, {"type": "static-text", "position": [456, 598, 40, 2], "text": ""}, {"type": "static-text", "position": [512, 598, 40, 2], "text": ""}, {"type": "static-text", "position": [568, 598, 40, 2], "text": ""}, {"type": "static-text", "position": [624, 598, 40, 2], "text": ""}]}