{"desc": "Samyang Optics\u2019 range of lenses are specially designed to deliver a superior tactile experience which allows creatives to concentrate on the pure essence of photography and video. We aim for excellent customer satisfaction in the field of imaging.", "file_name": "AF-85mm-F1.4-FE-II-Launching-Poster_7c872639-ca70-4f74-892b-8a64d541f1ca_1440x640_crop_center.jpg", "size": [1024, 700], "layout": [{"type": "background", "position": [0, 0, 1024, 700], "text": ""}, {"type": "static-text", "position": [56, 253, 629, 76], "text": "The second generation."}, {"type": "static-text", "position": [56, 332, 629, 28], "text": "AF 85mm F1.4 FE II"}, {"type": "static-text", "position": [56, 395, 130, 52], "text": "SHOP NOW"}]}