{"desc": "We are an electric lift truck and ariel lift motor specialist. We provide complete service on all electric lift truck motors. We also specialize in high amp needs for your school bus, fire and EMS applications.", "file_name": "hero_1512x.jpg", "size": [1024, 530], "layout": [{"type": "static-text", "position": [55, 177, 914, 78], "text": "Northern Ohio's Largest"}, {"type": "static-text", "position": [169, 263, 686, 36], "text": "Alternator, Starter and DC Motor Warehouse."}, {"type": "background", "position": [0, 0, 1024, 475], "text": ""}]}