{"desc": "Confident Tiger designs made-to-order, true to size bras and briefs for sizes 28C-44L, 8-28. Consciously made with love in the UK.", "file_name": "slider-poppy.jpg", "size": [1024, 690], "layout": [{"type": "background", "position": [0, 0, 1024, 644], "text": ""}, {"type": "static-text", "position": [98, 209, 424, 75], "text": "Find the Perfect Fit"}, {"type": "static-text", "position": [98, 294, 534, 56], "text": "Use our bra calculator to find your true size (not your high street, +4 size)"}, {"type": "static-text", "position": [98, 377, 221, 54], "text": "Measure Your Bust"}, {"type": "image", "position": [396, 662, 7, 11], "text": ""}, {"type": "static-text", "position": [446, 662, 12, 12], "text": ""}, {"type": "static-text", "position": [481, 662, 12, 12], "text": ""}, {"type": "static-text", "position": [515, 662, 12, 12], "text": ""}, {"type": "image", "position": [571, 662, 7, 11], "text": ""}, {"type": "image", "position": [624, 661, 9, 14], "text": ""}]}