{"desc": "Gola Market is the India's Best Online Market Store.", "file_name": "58f82f03-f763-4ffb-91bd-ff69fdca86d1.png", "size": [1009, 535], "layout": [{"type": "background", "position": [0, 0, 1009, 535], "text": ""}, {"type": "static-text", "position": [15, 47, 294, 184], "text": "Enjoy Up to 55% OFF"}, {"type": "static-text", "position": [15, 169, 338, 185], "text": "with International Brands"}, {"type": "static-text", "position": [15, 432, 230, 22], "text": "We have everything you need."}, {"type": "image", "position": [436, 215, 40, 40], "text": ""}, {"type": "static-text", "position": [484, 212, 105, 46], "text": "98% Satisfied\nCustomers"}, {"type": "image", "position": [420, 195, 185, 80], "text": ""}]}