{"desc": "Natural herbal remedies to balance out your body system for vitiligo treatment, psoriasis treatment and eczema treatment. Visit us online today for our list of skin condition treatments!", "file_name": "phillip-larking-3tGxWVuSRBk-unsplash_78b28a4b-e79d-4b6b-8f81-235ae363813e_1440x640_crop_center.jpg", "size": [1024, 700], "layout": [{"type": "background", "position": [0, 0, 922, 670], "text": ""}, {"type": "static-text", "position": [56, 231, 629, 151], "text": "Natural Herbal Remedies for Skin Health"}, {"type": "static-text", "position": [56, 386, 629, 84], "text": "Our Approach is to bring harmony and balance to your body's system, inside and out, because your skin is a mirror reflecting the state of your internal health."}]}