{"desc": "The sleep supplement of choice for Navy SEALs, pro athletes, and C-level executives, Sleep Remedy is designed to naturally decreases stress hormones while boosting relaxation chemistry for a deeply restorative sleep.", "file_name": "Sleep-Remedy-Capsules_e03bfa27-3dc4-4dce-bf30-a3aff5724212_1600x.png", "size": [1024, 448], "layout": [{"type": "background", "position": [0, 0, 1024, 448], "text": ""}, {"type": "static-text", "position": [113, 106, 369, 159], "text": "Give Yourself Permission To Sleep"}, {"type": "link-button", "position": [113, 286, 152, 50], "text": "GET SLEEP"}]}