{"desc": "At Weber\u2019s Wonders, we are obsessed to create and share happiness. We develop our high-value products for your comfort and joy. All our products are handy and simple to use and designed to ease your day to day.", "file_name": "Slider_Web_2_1080x.jpg", "size": [1024, 540], "layout": [{"type": "background", "position": [0, 0, 1024, 485], "text": ""}, {"type": "image", "position": [426, 453, 11, 11], "text": ""}, {"type": "image", "position": [539, 453, 11, 11], "text": ""}, {"type": "image", "position": [405, 437, 169, 44], "text": ""}, {"type": "image", "position": [592, 453, 10, 10], "text": ""}]}