{"desc": "Deew, weed spelled backwards, is a hemp beauty and wellness brand. Celebrating the benefits of cannabis without the stigma with our curated collection of cannabis infused beauty #youdeewyou", "file_name": "deew_products_aug20219edited--edited-1642102998456.jpg", "size": [1039, 610], "layout": [{"type": "static-text", "position": [356, 112, 574, 295], "text": "Say goodbye to dry skin with Body Buzz"}, {"type": "static-text", "position": [418, 457, 172, 19], "text": "+ ADD TO CART | $44"}, {"type": "background", "position": [0, 0, 1039, 610], "text": ""}]}