{"desc": "McBee\u2019s online education platform, Post-Acute Academy, hosts hundreds of courses, series, and one-time trainings aimed at home care, hospice, skilled nursing facilities staff and clinicians. Cloud-based system makes it easy to train when it fits into your staff's schedule.", "file_name": "McBee_Post-Acute_Academy-08-01_1024x440_crop_center.png", "size": [1024, 440], "layout": [{"type": "background", "position": [0, 0, 1024, 440], "text": ""}, {"type": "static-text", "position": [410, 119, 514, 122], "text": "Self-paced, on-demand post-acute education to maximize your potential."}, {"type": "link-button", "position": [717, 271, 207, 51], "text": "COURSE CATALOG"}]}