{"desc": "Polka Pop is India's first brand to serve naturally flavored sparkling water with zero calories and no added sugar. Supporting a sustainable lifestyle choice, this healthy drink is available in four flavors, i.e. lemon-lime, orange, peach, and cranberry. The fizz makes this the best mix for cocktails and mocktails.", "file_name": "HP_Banner-1_Desktop_34624b61-0d0d-414c-82e0-b22ccb615548_1080x.jpg", "size": [1024, 480], "layout": [{"type": "background", "position": [0, 0, 1024, 480], "text": ""}, {"type": "static-text", "position": [52, 98, 459, 145], "text": "A drink so good,\nyou go WTF?!*"}, {"type": "static-text", "position": [52, 264, 459, 56], "text": "India's first homegrown flavoured\nSparkling Water brand"}, {"type": "link-button", "position": [52, 334, 143, 48], "text": "Shop Now"}]}