{"desc": "ZHT Performance was born from our passion for precision machining and one-off road machines that don't follow the herd. Breaking boundaries, striving for a unique-pro-custom ride that only you can dream up? We will work with you & your overhaul car shop to get you in front, driving the tires off our design.", "file_name": "FRONT_REV-4_1080x.jpg", "size": [1024, 567], "layout": [{"type": "static-text", "position": [55, 166, 914, 86], "text": "Precision. CNC Machining. Custom. Automotive. Billet Parts. ZHTPerformance"}, {"type": "link-button", "position": [420, 298, 184, 46], "text": "QUOTE MY PART"}, {"type": "background", "position": [0, 0, 1024, 512], "text": ""}]}