{"desc": "The most vast selection of Canvas wall art prints on the web. Top quality and unbeatable price. With multiple production facilities in USA, Canada, Australia & the UK, we are better suited to handle your wall decor needs than anyone!", "file_name": "1920-2_7c1b8203-77c1-45e4-8df4-497fe4be4f86.jpg", "size": [1024, 500], "layout": [{"type": "background", "position": [0, 0, 988, 483], "text": ""}, {"type": "static-text", "position": [57, 105, 366, 39], "text": "Dr. Suess' rare \"Midnight Paintings\""}, {"type": "static-text", "position": [46, 159, 368, 99], "text": "The little known collection\nof dark and mysterious\nworks by Suess"}, {"type": "link-button", "position": [57, 327, 144, 31], "text": "SHOP NOW"}, {"type": "button", "position": [497, 454, 20, 20], "text": "1"}, {"type": "image", "position": [497, 454, 8, 8], "text": ""}, {"type": "button", "position": [522, 456, 20, 20], "text": "2"}, {"type": "image", "position": [521, 455, 6, 6], "text": ""}]}