{"desc": "PVDR Merchandise, Shirts, Gifts and Collectibles", "file_name": "gang_copy.jpg", "size": [1024, 705], "layout": [{"type": "static-text", "position": [55, 122, 914, 159], "text": "Welcome to PVDR's Gift Shop"}, {"type": "static-text", "position": [169, 299, 686, 158], "text": "All proceeds support the donkeys of the Peaceful Valley Donkey Rescue.\nThis is our newly updated store, if you find any errors please email giftshop@pvdr.org"}, {"type": "link-button", "position": [441, 484, 142, 41], "text": "COLLECTIONS"}, {"type": "background", "position": [0, 0, 1024, 650], "text": ""}]}