{"desc": "Oasis Healing Academy is the best natural herbal supplements online store to buy natural healing herpes in Dallas, Baltimore, Maryland, and New York areas. Best place for natural herbs to help you live a healthier life. Order today!", "file_name": "herbal-vitamin_1080x.jpg", "size": [1024, 705], "layout": [{"type": "static-text", "position": [55, 225, 914, 157], "text": "USING OUTSIDE HEALING INSIDE"}, {"type": "static-text", "position": [169, 390, 686, 35], "text": "Organic Herbal Supplements"}, {"type": "background", "position": [0, 0, 1024, 650], "text": ""}]}