{"desc": "Correct Merch is the premier retailer of essential streetwear including major brands like Nike, adidas, Air Jordan, Supreme, Off-White, and more.", "file_name": "0-3_41309aae-9532-43fb-b48d-eec9c848141a.jpg", "size": [1034, 700], "layout": [{"type": "background", "position": [0, 0, 1034, 700], "text": ""}, {"type": "static-text", "position": [36, 275, 393, 16], "text": "All Star Game Release"}, {"type": "static-text", "position": [36, 285, 393, 52], "text": "Correct x Ball Dawgs"}, {"type": "static-text", "position": [165, 381, 134, 42], "text": "SHOP NOW"}, {"type": "button", "position": [501, 671, 12, 19], "text": "1"}, {"type": "button", "position": [521, 671, 12, 19], "text": "2"}]}