{"desc": "Unique handmade leather bags, beaded, bags, earrings, and more.", "file_name": "AB080BCB-01C0-4D7C-8894-AAFDA33C3F97_1080x.jpg", "size": [1024, 522], "layout": [{"type": "image", "position": [32, 0, 230, 522], "text": ""}, {"type": "background", "position": [44, 0, 948, 522], "text": ""}, {"type": "static-text", "position": [51, 11, 46, 46], "text": ""}, {"type": "button", "position": [452, 479, 20, 20], "text": "1"}, {"type": "button", "position": [472, 479, 20, 20], "text": "2"}, {"type": "button", "position": [492, 479, 20, 20], "text": "3"}, {"type": "button", "position": [512, 479, 20, 20], "text": "4"}, {"type": "button", "position": [532, 479, 20, 20], "text": "5"}, {"type": "button", "position": [552, 479, 20, 20], "text": "6"}]}