{"desc": "Australian designed natural soy candles and body products inspired by the landscape of the Mornington Peninsula.", "file_name": "birch-bg-body.jpg", "size": [1024, 986], "layout": [{"type": "image", "position": [70, 56, 885, 277], "text": ""}, {"type": "image", "position": [55, 42, 914, 305], "text": ""}, {"type": "image", "position": [55, 388, 287, 144], "text": ""}, {"type": "image", "position": [368, 388, 287, 144], "text": ""}, {"type": "image", "position": [55, 574, 221, 221], "text": ""}, {"type": "static-text", "position": [76, 819, 147, 18], "text": "Ebony Candle - Aqua"}, {"type": "static-text", "position": [76, 844, 41, 15], "text": "Pamilli"}, {"type": "static-text", "position": [76, 870, 179, 22], "text": "$39.95"}, {"type": "image", "position": [55, 574, 221, 340], "text": ""}, {"type": "image", "position": [286, 574, 221, 221], "text": ""}, {"type": "static-text", "position": [307, 819, 157, 37], "text": "Ebony Candle - Basil & Lime"}, {"type": "static-text", "position": [307, 862, 41, 15], "text": "Pamilli"}, {"type": "static-text", "position": [307, 889, 179, 22], "text": "$39.95"}, {"type": "image", "position": [286, 574, 221, 359], "text": ""}, {"type": "image", "position": [517, 574, 221, 221], "text": ""}, {"type": "static-text", "position": [538, 819, 118, 37], "text": "Ebony Candle - Blackberry & Bay"}, {"type": "static-text", "position": [538, 862, 41, 15], "text": "Pamilli"}, {"type": "static-text", "position": [538, 889, 179, 22], "text": "$39.95"}, {"type": "image", "position": [517, 574, 221, 359], "text": ""}, {"type": "image", "position": [748, 574, 221, 221], "text": ""}, {"type": "static-text", "position": [769, 819, 160, 37], "text": "Ebony Candle - Rose & Lychee"}, {"type": "static-text", "position": [769, 862, 41, 15], "text": "Pamilli"}, {"type": "static-text", "position": [769, 889, 179, 22], "text": "$39.95"}, {"type": "image", "position": [748, 574, 221, 359], "text": ""}, {"type": "background", "position": [0, 0, 1024, 986], "text": ""}]}