{"desc": "The Merrimack Company is rooted in three pillars: community, nature, and adventure. We are a provider of high-quality, eco-friendly and sustainable apparel and accessories perfectly suited for any adventure. Stay Adventurous", "file_name": "E3133242-262B-4885-818B-B358ED0CA72F_1080x.jpg", "size": [1024, 705], "layout": [{"type": "background", "position": [0, 0, 1024, 650], "text": ""}, {"type": "static-text", "position": [55, 166, 914, 159], "text": "STAY ADVENTUROUS WITH SUSTAINABLE APPAREL"}, {"type": "static-text", "position": [60, 335, 903, 62], "text": "HIGH QUALITY GEAR THAT'S PERFECTLY SUITED FOR YOUR NEXT ADVENTURE - MADE FROM ORGANIC AND RECYCLED MATERIALS."}, {"type": "link-button", "position": [418, 431, 188, 51], "text": "BROWSE PRODUCTS"}]}