{"desc": "Hunting and Fishing Apparel engineered and designed for the Midwest. Shirts, sweatshirts, hats, longsleeves, pants, jackets, and much more. 2% donated to local conservation.", "file_name": "DSC09510_1400x.progressive.jpg", "size": [1024, 682], "layout": [{"type": "background", "position": [0, 0, 1024, 682], "text": ""}, {"type": "static-text", "position": [420, 181, 203, 53], "text": "THE ALL NEW"}, {"type": "static-text", "position": [420, 247, 551, 173], "text": "HIGH NOON BUTTON-DOWN"}, {"type": "static-text", "position": [420, 432, 286, 53], "text": "[ NOW AVAILABLE ]"}, {"type": "static-text", "position": [392, 646, 40, 4], "text": ""}, {"type": "static-text", "position": [432, 646, 40, 4], "text": ""}, {"type": "static-text", "position": [472, 646, 40, 4], "text": ""}, {"type": "static-text", "position": [512, 646, 40, 4], "text": ""}, {"type": "static-text", "position": [552, 646, 40, 4], "text": ""}, {"type": "static-text", "position": [592, 646, 40, 4], "text": ""}]}